indi_aws/__init__.py
indi_aws/aws_utils.py
indi_aws/fetch_creds.py
INDI_Tools-0.0.6.dist-info/DESCRIPTION.rst
INDI_Tools-0.0.6.dist-info/metadata.json
INDI_Tools-0.0.6.dist-info/WHEEL
INDI_Tools-0.0.6.dist-info/RECORD
INDI_Tools-0.0.6.dist-info/top_level.txt
INDI_Tools-0.0.6.dist-info/METADATA
indi_schedulers/__init__.py
indi_schedulers/cluster_templates.py
indi_schedulers/run_example.py
