Metadata-Version: 2.0
Name: INDI-Tools
Version: 0.0.6
Summary: Python utilities developed by FCP-INDI
Home-page: https://github.com/FCP-INDI/INDI-Tools
Author: Daniel Clark
Author-email: daniel.clark@childmind.org
License: UNKNOWN
Platform: UNKNOWN
Requires-Dist: botocore
Requires-Dist: boto3
